fsh_validator/__init__.py
fsh_validator/__main__.py
fsh_validator/cli.py
fsh_validator/fhir_resources.py
fsh_validator/fsh_validator.py
fsh_validator/fshpath.py
fsh_validator-0.3.5.dist-info/AUTHORS.rst
fsh_validator-0.3.5.dist-info/LICENSE
fsh_validator-0.3.5.dist-info/METADATA
fsh_validator-0.3.5.dist-info/WHEEL
fsh_validator-0.3.5.dist-info/entry_points.txt
fsh_validator-0.3.5.dist-info/top_level.txt
fsh_validator-0.3.5.dist-info/RECORD
