Metadata-Version: 2.1
Name: fsh-validator
Version: 0.3.5
Summary: FHIR Shorthand Validator unshortens fsh input and validates all defined instances against their profiles.
Home-page: https://github.com/glichtner/fsh-validator
Author: Gregor Lichtner
License: BSD license
Keywords: fsh-validator
Classifier: Development Status :: 2 - Pre-Alpha
Classifier: Intended Audience :: Developers
Classifier: License :: OSI Approved :: BSD License
Classifier: Natural Language :: English
Classifier: Programming Language :: Python :: 3
Classifier: Programming Language :: Python :: 3.6
Classifier: Programming Language :: Python :: 3.7
Classifier: Programming Language :: Python :: 3.8
Requires-Python: >=3.6
License-File: LICENSE
License-File: AUTHORS.rst
Requires-Dist: jsonpath-ng >=1.5.3
Requires-Dist: pandas >=1.2.4
Requires-Dist: openpyxl >=3.0.9
Requires-Dist: tabulate >=0.8.9
Requires-Dist: pyyaml >=5.4.1
